fluxhive/__init__.py
fluxhive/cli/__init__.py
fluxhive/cli/fluxhive.py
fluxhive/core/__init__.py
fluxhive/core/control_plane.py
fluxhive/core/exceptions.py
fluxhive/core/manager.py
fluxhive/core/models.py
fluxhive/core/runner.py
fluxhive/services/__init__.py
fluxhive/services/gpu_monitor.py
fluxhive/services/gpu_service.py
fluxhive/utils/__init__.py
fluxhive/utils/config.py
fluxhive/utils/crypto.py
fluxhive/utils/shell.py
fluxhive-0.2.0.dist-info/licenses/LICENSE
fluxhive-0.2.0.dist-info/METADATA
fluxhive-0.2.0.dist-info/WHEEL
fluxhive-0.2.0.dist-info/entry_points.txt
fluxhive-0.2.0.dist-info/top_level.txt
fluxhive-0.2.0.dist-info/RECORD
